{
  "global_vision": "Enable transformative AI solutions for humanity.",
  "long_term_goals": [
    {
      "objective": "Achieve global AI-augmented healthcare",
      "timeline": "2030",
      "metrics": ["95% accuracy in diagnosis", "80% global adoption"]
    },
    {
      "objective": "Promote AI-driven education accessibility",
      "timeline": "2028",
      "metrics": ["90% student satisfaction", "Accessible in 150 countries"]
    }
  ],
  "short_term_goals": [
    {
      "objective": "Improve anomaly detection efficiency",
      "timeline": "2024",
      "metrics": ["Reduce false positive rate by 20%", "Deploy in 50 enterprises"]
    },
    {
      "objective": "Deploy real-time monitoring systems",
      "timeline": "2023",
      "metrics": ["Implementation in 10 pilot projects", "99.9% uptime"]
    }
  ],
  "core_values": ["Innovation", "Integrity", "Sustainability"]
}